vidtoolz_shorts/__init__.py
vidtoolz_shorts/shorts.py
vidtoolz_shorts-0.0.3.dist-info/licenses/LICENSE
vidtoolz_shorts-0.0.3.dist-info/METADATA
vidtoolz_shorts-0.0.3.dist-info/WHEEL
vidtoolz_shorts-0.0.3.dist-info/entry_points.txt
vidtoolz_shorts-0.0.3.dist-info/top_level.txt
vidtoolz_shorts-0.0.3.dist-info/RECORD
