Metadata-Version: 2.4
Name: vidtoolz-shorts
Version: 0.0.3
Summary: Create shorts from long form videos
Author: Sukhbinder Singh
License: Apache-2.0
Project-URL: Homepage, https://github.com/sukhbinder/vidtoolz-shorts
Project-URL: Changelog, https://github.com/sukhbinder/vidtoolz-shorts/releases
Project-URL: Issues, https://github.com/sukhbinder/vidtoolz-shorts/issues
Project-URL: CI, https://github.com/sukhbinder/vidtoolz-shorts/actions
Classifier: License :: OSI Approved :: Apache Software License
License-File: LICENSE
Requires-Dist: vidtoolz
Provides-Extra: test
Requires-Dist: pytest; extra == "test"
Dynamic: license-file
